picsellia_connexion_services/__init__.py
picsellia_connexion_services/abstract_cached_connexions.py
picsellia_connexion_services/abstract_service_connexion.py
picsellia_connexion_services/cached_connexions.py
picsellia_connexion_services/exceptions.py
picsellia_connexion_services/jwt_service.py
picsellia_connexion_services/mock_cached_connexions.py
picsellia_connexion_services/mock_service_connexion.py
picsellia_connexion_services/token_service.py
picsellia_connexion_services-0.2.1.dist-info/WHEEL
picsellia_connexion_services-0.2.1.dist-info/LICENSE
picsellia_connexion_services-0.2.1.dist-info/METADATA
picsellia_connexion_services-0.2.1.dist-info/RECORD
