Metadata-Version: 2.1
Name: picsellia-connexion-services
Version: 0.2.1
Summary: Package for connection to Picsellia platforms with some wrapper around requests library
License: MIT
Author: Thomas Darget
Author-email: thomas.darget@picsellia.com
Requires-Python: >=3.7,<4.0
Classifier: License :: OSI Approved :: MIT License
Classifier: Programming Language :: Python :: 3
Classifier: Programming Language :: Python :: 3.7
Classifier: Programming Language :: Python :: 3.8
Classifier: Programming Language :: Python :: 3.9
Classifier: Programming Language :: Python :: 3.10
Classifier: Programming Language :: Python :: 3.11
Requires-Dist: requests (>=2.28,<3.0)
